alignak_module_mongo_logs/__init__.py
alignak_module_mongo_logs/logevent.py
alignak_module_mongo_logs/logs.py
alignak_module_mongo_logs/etc/__init__.py
alignak_module_mongo_logs/etc/alignak.d/alignak-module-mongo-logs.ini
alignak_module_mongo_logs/etc/arbiter/modules/mod-mongo-logs.cfg
alignak_module_mongo_logs-1.1.0.data/data/share/alignak/etc/alignak.d/alignak-module-mongo-logs.ini
alignak_module_mongo_logs-1.1.0.data/data/share/alignak/etc/arbiter/modules/mod-mongo-logs.cfg
alignak_module_mongo_logs-1.1.0.dist-info/AUTHORS
alignak_module_mongo_logs-1.1.0.dist-info/LICENSE
alignak_module_mongo_logs-1.1.0.dist-info/METADATA
alignak_module_mongo_logs-1.1.0.dist-info/WHEEL
alignak_module_mongo_logs-1.1.0.dist-info/top_level.txt
alignak_module_mongo_logs-1.1.0.dist-info/RECORD
