Metadata-Version: 2.1
Name: alignak-module-mongo-logs
Version: 1.1.0
Summary: Alignak - Broker module for the monitoring logs, directy store to Mongo DB
Home-page: https://github.com/Alignak-monitoring-contrib/alignak-modules-mongo-logs
Author: Frédéric Mohier
Author-email: frederic.mohier@alignak.net
License: GNU Affero General Public License, version 3
Keywords: alignak monitoring module logs
Platform: UNKNOWN
Classifier: Development Status :: 5 - Production/Stable
Classifier: Environment :: Console
Classifier: Intended Audience :: Developers
Classifier: Intended Audience :: System Administrators
Classifier: License :: OSI Approved :: GNU Affero General Public License v3 or later (AGPLv3+)
Classifier: Natural Language :: English
Classifier: Programming Language :: Python
Classifier: Topic :: System :: Monitoring
Classifier: Topic :: System :: Systems Administration
